assep/__init__.py
assep/anafas.py
assep/anarede.py
assep/atp-Nathan.py
assep/atp.py
assep/barra.py
assep/base_cc.py
assep/decks.py
assep/linha.py
assep/plt.py
assep/trafo_3enr.py
assep-0.6.0.dist-info/licenses/LICENSE
assep-0.6.0.dist-info/METADATA
assep-0.6.0.dist-info/WHEEL
assep-0.6.0.dist-info/top_level.txt
assep-0.6.0.dist-info/RECORD
