Metadata-Version: 2.4
Name: assep
Version: 0.6.0
Summary: Automações em Python para auxiliar estudos em sistemas elétricos de potência
Home-page: https://github.com/nkbueno/ASSEP
Author: Nathan Kelvi de Almeida Bueno
Author-email: nathankelvi@gmail.com
License-File: LICENSE
Requires-Dist: pandas
Requires-Dist: numpy
Requires-Dist: easygui
Requires-Dist: plotly
Requires-Dist: matplotlib
Requires-Dist: seaborn
Requires-Dist: xlsxwriter
Requires-Dist: pyarrow
Requires-Dist: bs4
Requires-Dist: selenium
Requires-Dist: datetime
Requires-Dist: requests
Requires-Dist: scipy
Requires-Dist: python-docx
Dynamic: author
Dynamic: author-email
Dynamic: description
Dynamic: description-content-type
Dynamic: home-page
Dynamic: license-file
Dynamic: requires-dist
Dynamic: summary
